ropyRoblox/RobloxAIO.py
ropyRoblox/__init__.py
ropyRoblox-0.0.2.dist-info/METADATA
ropyRoblox-0.0.2.dist-info/WHEEL
ropyRoblox-0.0.2.dist-info/top_level.txt
ropyRoblox-0.0.2.dist-info/RECORD
