Metadata-Version: 2.1
Name: ropyRoblox
Version: 0.0.2
Summary: Roblox Interaction Tool
Home-page: UNKNOWN
Author: IDSIFPQ28TBY3quSjnmPuA
Author-email: IDSIFPQ28TBY3quSjnmPuA@gmail.com
License: UNKNOWN
Keywords: python,roblox,interaction,multi tool,requests
Platform: UNKNOWN
Classifier: Development Status :: 1 - Planning
Classifier: Intended Audience :: Developers
Classifier: Programming Language :: Python :: 3
Classifier: Operating System :: Unix
Classifier: Operating System :: MacOS :: MacOS X
Classifier: Operating System :: Microsoft :: Windows
Requires-Dist: requests
